omegaconf/__init__.py
omegaconf/_impl.py
omegaconf/_utils.py
omegaconf/base.py
omegaconf/basecontainer.py
omegaconf/dictconfig.py
omegaconf/errors.py
omegaconf/grammar_parser.py
omegaconf/grammar_visitor.py
omegaconf/listconfig.py
omegaconf/nodes.py
omegaconf/omegaconf.py
omegaconf/py.typed
omegaconf/typing.py
omegaconf/version.py
omegaconf/grammar/__init__.py
omegaconf/grammar/gen/OmegaConfGrammarLexer.py
omegaconf/grammar/gen/OmegaConfGrammarParser.py
omegaconf/grammar/gen/OmegaConfGrammarParserListener.py
omegaconf/grammar/gen/OmegaConfGrammarParserVisitor.py
omegaconf/grammar/gen/__init__.py
omegaconf/resolvers/__init__.py
omegaconf/resolvers/oc/__init__.py
omegaconf/resolvers/oc/dict.py
omegaconf/vendor/__init__.py
omegaconf/vendor/antlr4/BufferedTokenStream.py
omegaconf/vendor/antlr4/CommonTokenFactory.py
omegaconf/vendor/antlr4/CommonTokenStream.py
omegaconf/vendor/antlr4/FileStream.py
omegaconf/vendor/antlr4/InputStream.py
omegaconf/vendor/antlr4/IntervalSet.py
omegaconf/vendor/antlr4/LL1Analyzer.py
omegaconf/vendor/antlr4/Lexer.py
omegaconf/vendor/antlr4/ListTokenSource.py
omegaconf/vendor/antlr4/Parser.py
omegaconf/vendor/antlr4/ParserInterpreter.py
omegaconf/vendor/antlr4/ParserRuleContext.py
omegaconf/vendor/antlr4/PredictionContext.py
omegaconf/vendor/antlr4/Recognizer.py
omegaconf/vendor/antlr4/RuleContext.py
omegaconf/vendor/antlr4/StdinStream.py
omegaconf/vendor/antlr4/Token.py
omegaconf/vendor/antlr4/TokenStreamRewriter.py
omegaconf/vendor/antlr4/Utils.py
omegaconf/vendor/antlr4/__init__.py
omegaconf/vendor/antlr4/_pygrun.py
omegaconf/vendor/antlr4/atn/ATN.py
omegaconf/vendor/antlr4/atn/ATNConfig.py
omegaconf/vendor/antlr4/atn/ATNConfigSet.py
omegaconf/vendor/antlr4/atn/ATNDeserializationOptions.py
omegaconf/vendor/antlr4/atn/ATNDeserializer.py
omegaconf/vendor/antlr4/atn/ATNSimulator.py
omegaconf/vendor/antlr4/atn/ATNState.py
omegaconf/vendor/antlr4/atn/ATNType.py
omegaconf/vendor/antlr4/atn/LexerATNSimulator.py
atopile_omegaconf-2.4.0.dev1.dist-info/LICENSE
atopile_omegaconf-2.4.0.dev1.dist-info/METADATA
atopile_omegaconf-2.4.0.dev1.dist-info/WHEEL
atopile_omegaconf-2.4.0.dev1.dist-info/top_level.txt
atopile_omegaconf-2.4.0.dev1.dist-info/RECORD
