Metadata-Version: 2.1
Name: atopile-omegaconf
Version: 2.4.0.dev1
Summary: A flexible configuration library
Home-page: https://github.com/omry/omegaconf
Author: Omry Yadan
Author-email: omry@yadan.net
Keywords: yaml configuration config
Classifier: Programming Language :: Python :: 3.8
Classifier: Programming Language :: Python :: 3.9
Classifier: Programming Language :: Python :: 3.10
Classifier: Programming Language :: Python :: 3.11
Classifier: License :: OSI Approved :: BSD License
Classifier: Operating System :: OS Independent
Requires-Python: >=3.8
License-File: LICENSE
Requires-Dist: PyYAML >=5.1.0
Requires-Dist: typing-extensions ; python_version <= "3.9"
Requires-Dist: dataclasses ; python_version == "3.6"
